{
  "pageNumber": 3,
  "totalPages": 3,
  "issues": [
    {
      "id": 17,
      "status": "Fixed",
      "summary": "Need way to name where apps are publicly",
      "labels": [
        "Type-Enhancement",
        "Priority-Medium"
      ],
      "stars": 1,
      "commentCount": 3
    },
    {
      "id": 16,
      "status": "Fixed",
      "summary": "Finding app.yaml is done incorrectly on jaiku",
      "labels": [
        "Type-Defect",
        "Priority-Medium",
        "Usability"
      ],
      "stars": 1,
      "commentCount": 4
    },
    {
      "id": 15,
      "status": "Fixed",
      "summary": "Current image type is only c1.xlarge",
      "labels": [
        "Type-Enhancement",
        "Priority-Medium",
        "Usability"
      ],
      "stars": 1,
      "commentCount": 5
    }
  ]
}
